<resource endian="Little" locale="0" unknown="0" tag="TextWeb">
  <message>
    <original xml:space="preserve">ヒッ――ヒヒッ！</original>
  </message>
  <message>
    <original xml:space="preserve">この洞窟の中にはとっても珍しい
花が咲いているのさ</original>
  </message>
  <message>
    <original xml:space="preserve">それをさ、採ってきてくれないかい？
ヒヒッ！</original>
  </message>
  <message>
    <original xml:space="preserve">ヒッ――ヒヒッ！</original>
  </message>
  <message>
    <original xml:space="preserve">この洞窟の中にはとっても珍しい
花が咲いているのさ</original>
  </message>
  <message>
    <original xml:space="preserve">それをさ、採ってきてくれないかい？</original>
  </message>
  <message>
    <original xml:space="preserve">数はそこそこあるとうれしいね
ヒヒッ！</original>
  </message>
  <message>
    <original xml:space="preserve">ヒッ――ヒヒッ！</original>
  </message>
  <message>
    <original xml:space="preserve">この洞窟の中にはとっても珍しい
花が咲いているのさ</original>
  </message>
  <message>
    <original xml:space="preserve">それをさ、採ってきてくれないかい？
かなりいっぱい欲しいところだね
ヒヒッ！</original>
  </message>
  <message>
    <original xml:space="preserve">ヒッ――ヒヒッ！
よく見つけたね</original>
  </message>
  <message>
    <original xml:space="preserve">ん？　どうしたんだ――
ほら、用は済んだからさっさとお行き</original>
  </message>
  <message>
    <original xml:space="preserve">ヒッ――ヒヒッ！
よく見つけたね</original>
  </message>
  <message>
    <original xml:space="preserve">ん？　どうしたんだ――</original>
  </message>
  <message>
    <original xml:space="preserve">花をどうするつもりかって？
そんなのあたしの勝手だろうよ
ヒヒッ！</original>
  </message>
  <message>
    <original xml:space="preserve">ヒッ――ヒヒッ！
そうそう、これこれ――
よく見つけたね</original>
  </message>
  <message>
    <original xml:space="preserve">ん？　どうしたんだ――</original>
  </message>
  <message>
    <original xml:space="preserve">花をどうするつもりかって？
これはね――孫にあげるのさ
あの子のお墓に手向けようと思ってね</original>
  </message>
  <message>
    <original xml:space="preserve">こんなバァの頼みを聞いてくれて
本当に感謝しているよ</original>
  </message>
  <message>
    <original xml:space="preserve">あんたに頼みごとをしていなかったかね？
洞窟だよ、洞窟――ヒヒッ！</original>
  </message>
</resource>