<resource endian="Little" locale="0" unknown="0" tag="TextWeb">
  <message>
    <original xml:space="preserve">お、そうだ！　お前さんにちょっと頼みがあるんだ</original>
  </message>
  <message>
    <original xml:space="preserve">この辺りってほら、遺跡が多いだろ？
俺ってその遺物を商売にしてるわけなんだけど
問題が発生してさ</original>
  </message>
  <message>
    <original xml:space="preserve">南東の街道に、でかい魔像が出たらしいんだ
おかげで俺の客も怪我するわ、せっかくの遺物は
壊されるわで困っててさ</original>
  </message>
  <message>
    <original xml:space="preserve">そこで、どうだ？　ばっちり礼はするから
その魔像を何とかしてくれないか？</original>
  </message>
  <message>
    <original xml:space="preserve">あ、お前さん！
例の魔像の件、よろしく頼むぜ！</original>
  </message>
  <message>
    <original xml:space="preserve">しかし、魔像の装甲やメダルが
取れたら高値で売れそうだよな！</original>
  </message>
  <message>
    <original xml:space="preserve">おお、魔像をどかしてくれたんだな
いやぁ助かったよ！</original>
  </message>
  <message>
    <original xml:space="preserve">じゃ、約束通りあんたへの報酬を送っておくよ
もし何かあったらまたよろしくな</original>
  </message>
</resource>