<resource endian="Little" locale="0" unknown="0" tag="TextWeb">
  <message>
    <original xml:space="preserve">君、私はね
ここら一帯の土地のようすを調べているんだよ</original>
  </message>
  <message>
    <original xml:space="preserve">特に、ほら――地面を見たまえ
ところどころに淀んだ水が溜まっているだろう？</original>
  </message>
  <message>
    <original xml:space="preserve">私はこの毒性を持つ黒い水が
地下から湧き出ていることに
強い関心を持っているんだよ</original>
  </message>
  <message>
    <original xml:space="preserve">そんなわけでぜひ協力してくれないか
毒沼の付近で何か特徴的な物を見つけたら
持ってきて欲しいんだ
頼んだよ</original>
  </message>
  <message>
    <original xml:space="preserve">君、私はね
ここら一帯の土地のようすを調べているんだよ</original>
  </message>
  <message>
    <original xml:space="preserve">特に、ほら――地面を見たまえ
ところどころに黒淀んだ水が溜まっているだろう？</original>
  </message>
  <message>
    <original xml:space="preserve">あれは毒性を持つ黒い水が
地下から湧き出ているんだよ
そのせいかこの辺りはあまり草木が育たない</original>
  </message>
  <message>
    <original xml:space="preserve">この土地の地下には、水を毒物に変えてしまっている
原因があるはずなんだ――</original>
  </message>
  <message>
    <original xml:space="preserve">そんなわけでぜひ協力してくれないか
毒沼の付近で何か特徴的な物を見つけたら
持ってきて欲しいんだ
頼んだよ</original>
  </message>
  <message>
    <original xml:space="preserve">君、私はね
ここら一帯の土地のようすを調べているんだよ</original>
  </message>
  <message>
    <original xml:space="preserve">特に、ほら――地面を見たまえ
ところどころに淀んだ水が溜まっているだろう？</original>
  </message>
  <message>
    <original xml:space="preserve">あれは毒性を持つ黒い水が
地下から湧き出ているんだよ
その毒の成分についてすら
まだまだ分かっていないんだ</original>
  </message>
  <message>
    <original xml:space="preserve">この土地の地下には、我々が学ばねばならないことが
たくさん眠っている、そんな気がしてならないよ</original>
  </message>
  <message>
    <original xml:space="preserve">というわけでぜひ協力してくれないか
毒沼の付近で何か特徴的な物を見つけたら
持ってきて欲しいんだ
頼んだよ</original>
  </message>
  <message>
    <original xml:space="preserve">ほうほう、なるほど、これは参考になる
助かるよ――</original>
  </message>
  <message>
    <original xml:space="preserve">これからも研究を続けて
この土地の特性を解き明かして見せるよ</original>
  </message>
  <message>
    <original xml:space="preserve">今後も協力してくれると嬉しいね
また会おう</original>
  </message>
  <message>
    <original xml:space="preserve">ほうほう、なるほど、これは良い！
助かるよ――</original>
  </message>
  <message>
    <original xml:space="preserve">これからも研究を続けて
この土地の特性を解き明かして見せるよ</original>
  </message>
  <message>
    <original xml:space="preserve">今後も協力してくれると嬉しいね
また会おう</original>
  </message>
  <message>
    <original xml:space="preserve">ほうほう、おおおお、これは凄いね！
助かるよ――</original>
  </message>
  <message>
    <original xml:space="preserve">これからも研究を続けて
この土地の特性を解き明かして見せるよ</original>
  </message>
  <message>
    <original xml:space="preserve">この毒沼を抑えることができれば
もっとボルドも豊かになるはず――</original>
  </message>
  <message>
    <original xml:space="preserve">今後も共に協力してくれると嬉しいね
また会おう</original>
  </message>
  <message>
    <original xml:space="preserve">ああ、この土地の毒には気をつけたほうがいい
準備はしっかりとしていってくれ――</original>
  </message>
</resource>