<resource endian="Little" locale="0" unknown="0" tag="TextWeb">
  <message>
    <original xml:space="preserve">おっと、なんだ、脅かすなよ</original>
  </message>
  <message>
    <original xml:space="preserve">どうせオマエもここで
お宝を見つけようって魂胆だろ？</original>
  </message>
  <message>
    <original xml:space="preserve">なら――どうだ、俺と組まねえか
ひとまず、中の魔物を一掃してくれりゃいい
任せたぞ</original>
  </message>
  <message>
    <original xml:space="preserve">おいおい、なんだ、脅かすなよ</original>
  </message>
  <message>
    <original xml:space="preserve">どうせオマエもここで
お宝見つけて、ひと稼ぎしてやろうって魂胆だろ？</original>
  </message>
  <message>
    <original xml:space="preserve">なら――どうだ、俺と組まねえか
ひとまず、中の魔物を一掃してくれりゃいい</original>
  </message>
  <message>
    <original xml:space="preserve">魔物の中にはちょいと凶暴な奴もいるみたいだが
オマエならいけるだろう
任せたぞ</original>
  </message>
  <message>
    <original xml:space="preserve">おおっと、なんだ、脅かすなよ</original>
  </message>
  <message>
    <original xml:space="preserve">どうせオマエもここで
お宝見つけて、ひと財産稼いでやろうって魂胆だろ？</original>
  </message>
  <message>
    <original xml:space="preserve">なら――どうだ、俺と組まねえか
ひとまず、中の魔物を一掃してくれりゃいい</original>
  </message>
  <message>
    <original xml:space="preserve">魔物の中にはバカみたいに凶暴な奴もいるみたいだが
オマエならいけるよな
任せたぞ</original>
  </message>
  <message>
    <original xml:space="preserve">おお、やるじゃねえか</original>
  </message>
  <message>
    <original xml:space="preserve">これなら、俺たちで組めば随分稼げるぜ
気が向いたら、また声をかけてくれ</original>
  </message>
  <message>
    <original xml:space="preserve">おお、やるじゃねえか
すごいな、オマエ</original>
  </message>
  <message>
    <original xml:space="preserve">これなら、俺たちで組めば
毎晩、宿を貸し切って
酒盛りできるほど稼げるぜ</original>
  </message>
  <message>
    <original xml:space="preserve">気が向いたら、また声をかけてくれ</original>
  </message>
  <message>
    <original xml:space="preserve">おお、やるじゃねえか
オマエの腕前にはほんと、恐れ入ったよ</original>
  </message>
  <message>
    <original xml:space="preserve">これなら、俺たちで組めばそのうちに
豪勢な城がぶっ建つほど稼げるぜ</original>
  </message>
  <message>
    <original xml:space="preserve">気が向いたら、必ず声をかけてくれよ</original>
  </message>
  <message>
    <original xml:space="preserve">ほら、さっさとやっちまえよ</original>
  </message>
</resource>