<resource endian="Little" locale="0" unknown="0" tag="TextWeb">
  <message>
    <text xml:space="preserve">今度はなんだ？　奴らに聞かせるなよ</text>
  </message>
  <message>
    <text xml:space="preserve">なんだと！？
魔物を倒しただって？</text>
  </message>
  <message>
    <text xml:space="preserve">今、なんと言った？</text>
  </message>
  <message>
    <text xml:space="preserve">騎士団さんよ、人が悪いぜ
魔物はすっかり倒したらしいじゃねえか</text>
  </message>
  <message>
    <text xml:space="preserve">ったく！
おれたちは帰る！　ああ、帰るぞ！</text>
  </message>
  <message>
    <text xml:space="preserve">なんの話だ――</text>
  </message>
  <message>
    <text xml:space="preserve">おまえ、騎士団副長のハインツだろ？</text>
  </message>
  <message>
    <text xml:space="preserve">そこまで出世するってのは
よほど話のわかる奴に違いねえ</text>
  </message>
  <message>
    <text xml:space="preserve">だから、ここの魔物を退治したのは
あんたか部下の誰かってことにしておけ</text>
  </message>
  <message>
    <text xml:space="preserve">それから新入り、おまえ――</text>
  </message>
  <message>
    <text xml:space="preserve">いろいろ文句はあるだろうが全部飲み込め
疑問も飲み込め</text>
  </message>
  <message>
    <text xml:space="preserve">ここにいる全員、おまえの手柄は忘れない
だが、公式には騎士団が倒したことにする</text>
  </message>
  <message>
    <text xml:space="preserve">いいな？</text>
  </message>
  <message>
    <text xml:space="preserve">はん！　その手には乗るか！</text>
  </message>
  <message>
    <text xml:space="preserve">恩を売りつけようというのか？
貸しを作っておこうという魂胆か！？</text>
  </message>
  <message>
    <text xml:space="preserve">ハインツ！　</text>
  </message>
  <message>
    <text xml:space="preserve">はっ！</text>
  </message>
  <message>
    <text xml:space="preserve">怒声が木々に響き渡っているが――
揉め事ではないだろうな</text>
  </message>
  <message>
    <text xml:space="preserve">信じられないことだが、騎士と見れば
因縁をつける志の低い覚者もいるようだ</text>
  </message>
  <message>
    <text xml:space="preserve">まさか挑発に――</text>
  </message>
  <message>
    <text xml:space="preserve">とんでもありません！</text>
  </message>
  <message>
    <text xml:space="preserve">騎士団長さんよ、信じてやりな
こいつはおれたちの不作法をいさめただけだ</text>
  </message>
  <message>
    <text xml:space="preserve">ハインツたち、いい仕事をしたぜ？
魔物はもういない――静かなもんだ</text>
  </message>
  <message>
    <text xml:space="preserve">――ほう
任務はすでに完了したというのか</text>
  </message>
  <message>
    <text xml:space="preserve">ふむ――
レオから報告を受けて慌ててここへ来たが</text>
  </message>
  <message>
    <text xml:space="preserve">取り越し苦労だったようだな
では、一同、神殿へ戻るがいい</text>
  </message>
  <message>
    <text xml:space="preserve">よし、じゃあ、覚者も解散だ！</text>
  </message>
  <message>
    <text xml:space="preserve">お疲れだったな
特におまえ――よくこらえた、いい根性だ</text>
  </message>
</resource>