<resource endian="Little" locale="0" unknown="0" tag="TextWeb">
  <message>
    <key>CUSTOM_SKILL_COMMAND_06_68</key>
    <original xml:space="preserve">セットボタンを押して詠唱、詠唱完了で発動</original>
    <translation xml:space="preserve">Charge. Press the assigned button and wait for the
charge to finish.</translation>
  </message>
  <message>
    <key>CUSTOM_SKILL_COMMAND_06_72</key>
    <original xml:space="preserve">セットボタンを押して詠唱、詠唱完了で発動</original>
    <translation xml:space="preserve">Charge. Press the assigned button and wait for the
charge to finish.</translation>
  </message>
  <message>
    <key>CUSTOM_SKILL_COMMAND_06_74</key>
    <original xml:space="preserve">セットボタンを押して詠唱、詠唱完了で発動</original>
    <translation xml:space="preserve">Charge. Press the assigned button and wait for the
charge to finish.</translation>
  </message>
  <message>
    <key>CUSTOM_SKILL_COMMAND_06_71</key>
    <original xml:space="preserve">セットボタンを押して詠唱、詠唱完了で発動</original>
    <translation xml:space="preserve">Charge. Press the assigned button and wait for the
charge to finish.</translation>
  </message>
  <message>
    <key>CUSTOM_SKILL_COMMAND_06_69</key>
    <original xml:space="preserve">セットボタンを押して詠唱、詠唱完了で発動</original>
    <translation xml:space="preserve">Charge. Press the assigned button and wait for the
charge to finish.</translation>
  </message>
  <message>
    <key>CUSTOM_SKILL_COMMAND_06_73</key>
    <original xml:space="preserve">セットボタンを押して詠唱、詠唱完了で発動</original>
    <translation xml:space="preserve">Charge. Press the assigned button and wait for the
charge to finish.</translation>
  </message>
  <message>
    <key>CUSTOM_SKILL_COMMAND_06_75</key>
    <original xml:space="preserve">セットボタンを押して詠唱、詠唱完了で発動</original>
    <translation xml:space="preserve">Charge. Press the assigned button and wait for the
charge to finish.</translation>
  </message>
  <message>
    <key>CUSTOM_SKILL_COMMAND_06_70</key>
    <original xml:space="preserve">セットボタンを押して詠唱、詠唱完了で発動</original>
    <translation xml:space="preserve">Charge. Press the assigned button and wait for the
charge to finish.</translation>
  </message>
  <message>
    <key>CUSTOM_SKILL_COMMAND_06_76</key>
    <original xml:space="preserve">セットボタンを押して詠唱、詠唱完了で発動</original>
    <translation xml:space="preserve">Charge. Press the assigned button and wait for the
charge to finish.</translation>
  </message>
  <message>
    <key>CUSTOM_SKILL_COMMAND_06_78</key>
    <original xml:space="preserve">セットボタンを押して詠唱、詠唱完了で発動</original>
    <translation xml:space="preserve">Charge. Press the assigned button and wait for the
charge to finish.</translation>
  </message>
  <message>
    <key>CUSTOM_SKILL_COMMAND_06_77</key>
    <original xml:space="preserve">セットボタンを押して詠唱、詠唱完了で発動</original>
    <translation xml:space="preserve">Charge. Press the assigned button and wait for the
charge to finish.</translation>
  </message>
</resource>