<resource>
  <message>
    <original>貴様！　そこをどかんか！</original>
  </message>
  <message>
    <original>この場所はアッカー家当主ネド王子のものだ</original>
  </message>
  <message>
    <original>ふん、傷深くして、動けんか！</original>
  </message>
  <message>
    <original>来ると思っていたぞ、白竜の覚者よ</original>
  </message>
  <message>
    <original>ふんっ！（リアクションボイス）</original>
  </message>
  <message>
    <original>グウゥッ！！！（リアクションボイス）</original>
  </message>
  <message>
    <original>ンンッ！！！（リアクションボイス）</original>
  </message>
  <message>
    <original>クッ、待っていたとでも言うのか？
傷で動けなかったくせに</original>
  </message>
  <message>
    <original>傷？　この身は空ろだ</original>
  </message>
  <message>
    <original>空（から）？　そもそもあんた何者！？</original>
  </message>
  <message>
    <original>黒き竜に連なる、理から外れた者</original>
  </message>
  <message>
    <original>理の中の貴様らには理解できまい</original>
  </message>
  <message>
    <original>それよりもあの男の居場所を知りたくはないか？</original>
  </message>
  <message>
    <original>てめぇ――レオのことか！！</original>
  </message>
  <message>
    <original>わたしに剣を突き立て、危うくしたあの男――</original>
  </message>
  <message>
    <original>暗闇の海で溺れかけているわ</original>
  </message>
  <message>
    <original>ふざけんなよ――
話はてめえをぶっ倒してからだ！</original>
  </message>
  <message>
    <original>ぬんっ（リアクションボイス）</original>
  </message>
</resource>
