<resource endian="Little" locale="0" unknown="0" tag="TextWeb">
  <message>
    <key>entry_board_title_jp</key>
    <text xml:space="preserve">Entry Board</text>
  </message>
  <message>
    <key>entry_board_title_en</key>
    <text xml:space="preserve">Entry Board</text>
  </message>
  <message>
    <key>entry_board_comment</key>
    <text xml:space="preserve">Comment</text>
  </message>
  <message>
    <key>entry_board_leader</key>
    <text xml:space="preserve">募集主</text>
  </message>
  <message>
    <key>entry_board_entry</key>
    <text xml:space="preserve">Participants</text>
  </message>
  <message>
    <key>entry_board_recruit</key>
    <text xml:space="preserve">Recruit Members</text>
  </message>
  <message>
    <key>entry_board_search</key>
    <text xml:space="preserve">Search</text>
  </message>
  <message>
    <key>entry_board_param1</key>
    <text xml:space="preserve">&lt;VAL&gt; &lt;VAL&gt;</text>
  </message>
  <message>
    <key>entry_board_param2</key>
    <text xml:space="preserve">&lt;VAL&gt;/&lt;VAL&gt;</text>
  </message>
  <message>
    <key>entry_board_search_search_job</key>
    <text xml:space="preserve">Search Jobs Allowed</text>
  </message>
  <message>
    <key>entry_board_search_search</key>
    <text xml:space="preserve">Set Search Conditions</text>
  </message>
  <message>
    <key>entry_board_search_search_friend_friend</key>
    <text xml:space="preserve">Look for entries where friends are participating</text>
  </message>
  <message>
    <key>entry_board_search_search_name</key>
    <text xml:space="preserve">Search by Name</text>
  </message>
  <message>
    <key>entry_board_search_search_friend</key>
    <text xml:space="preserve">Search Friends</text>
  </message>
  <message>
    <key>entry_board_search_search_password</key>
    <text xml:space="preserve">No Password Set</text>
  </message>
  <message>
    <key>entry_board_search_search_clanmember</key>
    <text xml:space="preserve">Search Clan Members</text>
  </message>
  <message>
    <key>entry_board_search_all</key>
    <text xml:space="preserve">All</text>
  </message>
  <message>
    <key>entry_board_search_init</key>
    <text xml:space="preserve">Reset Search</text>
  </message>
  <message>
    <key>entry_board_search_word1</key>
    <text xml:space="preserve">～</text>
  </message>
  <message>
    <key>entry_board_search_exec_search</key>
    <text xml:space="preserve">Search</text>
  </message>
  <message>
    <key>entry_board_search_cancel</key>
    <text xml:space="preserve">Cancel</text>
  </message>
  <message>
    <key>entry_board_search_serach_level</key>
    <text xml:space="preserve">Search by Level</text>
  </message>
  <message>
    <key>entry_board_pop_reqruit_all</key>
    <text xml:space="preserve">All</text>
  </message>
  <message>
    <key>entry_board_pop_reqruit_reqruit</key>
    <text xml:space="preserve">Recruit</text>
  </message>
  <message>
    <key>entry_board_pop_reqruit_cancel</key>
    <text xml:space="preserve">Cancel</text>
  </message>
  <message>
    <key>entry_board_reqruit_entry</key>
    <text xml:space="preserve">Please setup your entry</text>
  </message>
  <message>
    <key>entry_board_reqruit_comment</key>
    <text xml:space="preserve">Comment</text>
  </message>
  <message>
    <key>entry_board_reqruit_level</key>
    <text xml:space="preserve">Level Restriction</text>
  </message>
  <message>
    <key>entry_board_reqruit_job</key>
    <text xml:space="preserve">Job Restriction</text>
  </message>
  <message>
    <key>entry_board_reqruit_password</key>
    <text xml:space="preserve">Set Password</text>
  </message>
  <message>
    <key>entry_board_reqruit_word1</key>
    <text xml:space="preserve">&lt;VAL&gt;.</text>
  </message>
  <message>
    <key>entry_board_reqruit_osusume</key>
    <text xml:space="preserve">Recommended</text>
  </message>
  <message>
    <key>entry_board_reqruit_reqruit</key>
    <text xml:space="preserve">Recruit</text>
  </message>
  <message>
    <key>entry_board_reqruit_cancel</key>
    <text xml:space="preserve">Cancel</text>
  </message>
  <message>
    <key>entry_board_reqruit_word2</key>
    <text xml:space="preserve">～</text>
  </message>
  <message>
    <key>entry_board_info_memberlist</key>
    <text xml:space="preserve">Member List</text>
  </message>
  <message>
    <key>entry_board_info_option</key>
    <text xml:space="preserve">Option</text>
  </message>
  <message>
    <key>entry_board_info_password_on</key>
    <text xml:space="preserve">【Password】</text>
  </message>
  <message>
    <key>entry_board_info_job_on</key>
    <text xml:space="preserve">【Jobs Specified】</text>
  </message>
  <message>
    <key>entry_board_info_word1</key>
    <text xml:space="preserve">&lt;VAL&gt;/&lt;VAL&gt;</text>
  </message>
  <message>
    <key>entry_board_pop_event_top_entry</key>
    <text xml:space="preserve">Participating</text>
  </message>
  <message>
    <key>entry_board_mission_info_reward</key>
    <text xml:space="preserve">Reward</text>
  </message>
  <message>
    <key>entry_board_mission_info_entry_num</key>
    <text xml:space="preserve">&lt;VAL&gt;人専用コンテンツ</text>
  </message>
  <message>
    <key>entry_board_mission_info_recommand</key>
    <text xml:space="preserve">推奨</text>
  </message>
  <message>
    <key>entry_board_mission_info_war_situation</key>
    <text xml:space="preserve">戦況</text>
  </message>
  <message>
    <key>entry_board_mission_info_decide</key>
    <text xml:space="preserve">OK</text>
  </message>
  <message>
    <key>entry_board_mission_info_cancel</key>
    <text xml:space="preserve">Cancel</text>
  </message>
  <message>
    <key>entry_board_search_designate_lv</key>
    <text xml:space="preserve">Specify Level</text>
  </message>
  <message>
    <key>entry_board_or_more</key>
    <text xml:space="preserve">or more</text>
  </message>
  <message>
    <key>entry_board_or_less</key>
    <text xml:space="preserve">or less</text>
  </message>
  <message>
    <key>entry_board_info_no</key>
    <text xml:space="preserve">戻る</text>
  </message>
  <message>
    <key>entry_board_info_member_check</key>
    <text xml:space="preserve">Check Members</text>
  </message>
  <message>
    <key>entry_board_info_limit_lv</key>
    <text xml:space="preserve">【Level Limit】</text>
  </message>
  <message>
    <key>entry_board_contents_title_e</key>
    <text xml:space="preserve">Contents</text>
  </message>
  <message>
    <key>entry_board_contents_title_j</key>
    <text xml:space="preserve">コンテンツ窓口</text>
  </message>
  <message>
    <key>entry_board_contents_event</key>
    <text xml:space="preserve">View Lestania News</text>
  </message>
  <message>
    <key>entry_board_mission_info_condition</key>
    <text xml:space="preserve">受注条件</text>
  </message>
  <message>
    <key>entry_board_info_no_designate_job</key>
    <text xml:space="preserve">Any Job</text>
  </message>
  <message>
    <key>entry_borad_contents_num</key>
    <text xml:space="preserve">&lt;VAL&gt;</text>
  </message>
  <message>
    <key>entry_board_info_memberlist_j</key>
    <text xml:space="preserve">Member List</text>
  </message>
  <message>
    <key>entry_board_enter_password</key>
    <text xml:space="preserve">Please enter your password.</text>
  </message>
  <message>
    <key>entry_board_btn_searth_another</key>
    <text xml:space="preserve">Search Again</text>
  </message>
  <message>
    <key>entry_board_set</key>
    <text xml:space="preserve">No</text>
  </message>
  <message>
    <key>entry_board_unset</key>
    <text xml:space="preserve">None</text>
  </message>
  <message>
    <key>entry_board_level_band</key>
    <text xml:space="preserve">min&lt;VAL&gt;～max&lt;VAL&gt;</text>
  </message>
  <message>
    <key>entry_board_unsatisfied</key>
    <text xml:space="preserve">You do not meet the recruitment conditions</text>
  </message>
  <message>
    <key>entry_board_lv_limit1</key>
    <text xml:space="preserve">Level Limit: </text>
  </message>
  <message>
    <key>entry_board_lv_limit2</key>
    <text xml:space="preserve">Level Limit</text>
  </message>
  <message>
    <key>entry_board_job_limit1</key>
    <text xml:space="preserve">Job Specified</text>
  </message>
  <message>
    <key>entry_board_job_limit2</key>
    <text xml:space="preserve">Job Specified:</text>
  </message>
  <message>
    <key>entry_board_pass_limit1</key>
    <text xml:space="preserve">Password:</text>
  </message>
  <message>
    <key>entry_board_pass_limit2</key>
    <text xml:space="preserve">Password Setting</text>
  </message>
  <message>
    <key>entry_board_time_gather</key>
    <text xml:space="preserve">Time:</text>
  </message>
  <message>
    <key>entry_board_num_menber</key>
    <text xml:space="preserve">Members:</text>
  </message>
  <message>
    <key>entry_board_is_cancel_make</key>
    <text xml:space="preserve">Do you want to cancel recruitment?</text>
  </message>
  <message>
    <key>entry_board_buttonguid_membercheck</key>
    <text xml:space="preserve">Confirm Party Members</text>
  </message>
  <message>
    <key>entry_board_fail_search</key>
    <text xml:space="preserve">There was 0 search results.</text>
  </message>
</resource>