<resource endian="Little" locale="0" unknown="0" tag="TextWeb">
  <message>
    <key>JMMH_MSG_ALLTASK_CLEAR_STR</key>
    <text xml:space="preserve">The challenge was finished and reported to the Job Master</text>
  </message>
  <message>
    <key>JMMH_MSG_LV_STR</key>
    <text xml:space="preserve">LV.</text>
  </message>
  <message>
    <key>JMMH_MSG_TASK_STR</key>
    <text xml:space="preserve">Report to the &lt;VAL&gt; Job Master to finish training</text>
  </message>
  <message>
    <key>JMMH_MSG_SLASH_STR</key>
    <text xml:space="preserve">/</text>
  </message>
  <message>
    <key>JMMH_MSG_BEAT_STR</key>
    <text xml:space="preserve">Defeat at minimum &lt;VAL LV&gt; &lt;NAME ENEMY&gt;!</text>
  </message>
  <message>
    <key>JMMH_MSG_EQUIP_STR</key>
    <text xml:space="preserve">を装備しろ！</text>
  </message>
  <message>
    <key>JMMH_MSG_MAX_STR</key>
    <text xml:space="preserve">MAX</text>
  </message>
  <message>
    <key>JMMH_MSG_JOB_MASTER_STR</key>
    <text xml:space="preserve">Job Master</text>
  </message>
  <message>
    <key>JMMH_MSG_JOB_MASTER_STR_JP</key>
    <text xml:space="preserve">Job Master</text>
  </message>
  <message>
    <key>JMMH_MSG_MASTER_HB_STR_JP</key>
    <text xml:space="preserve">Job Training Log</text>
  </message>
  <message>
    <key>JMMH_MSG_LV_STR_2</key>
    <text xml:space="preserve">Level</text>
  </message>
  <message>
    <key>JMMH_MSG_CUSTOM_SKILL_STR</key>
    <text xml:space="preserve">Custom Skills</text>
  </message>
  <message>
    <key>JMMH_MSG_ABILITY_STR</key>
    <text xml:space="preserve">Abilities</text>
  </message>
  <message>
    <key>JMMH_MSG_NEXT_STR</key>
    <text xml:space="preserve">Next</text>
  </message>
  <message>
    <key>JOBEXAM_MSG_DECIDE_STR</key>
    <text xml:space="preserve">OK</text>
  </message>
  <message>
    <key>JOBEXAM_MSG_SKILLGET_STR</key>
    <text xml:space="preserve">&lt;NAME SKILL&gt; is ready to learn</text>
  </message>
  <message>
    <key>JOBEXAM_MSG_ABILITYGET_STR</key>
    <text xml:space="preserve">&lt;NAME ABILITY&gt; is ready to learn</text>
  </message>
  <message>
    <key>JMMH_MSG_ENEMY_LEVEL_STR</key>
    <text xml:space="preserve">Defeat blood orb enemies!</text>
  </message>
  <message>
    <key>JMMH_MSG_MASTER_HB_STR</key>
    <text xml:space="preserve">Training Note</text>
  </message>
  <message>
    <key>JMMH_MSG_TASK_EXAM_STR</key>
    <text xml:space="preserve">Report to the Job Master to finish training</text>
  </message>
  <message>
    <key>JMMH_MSG_JOB_STR</key>
    <text xml:space="preserve">Jobs</text>
  </message>
  <message>
    <key>JMMH_MSG_NO_ORDER_STR</key>
    <text xml:space="preserve">No orders</text>
  </message>
</resource>