<resource endian="Little" locale="0" unknown="0" tag="TextWeb">
  <message>
    <text xml:space="preserve">（肩書なし）</text>
  </message>
  <message>
    <text xml:space="preserve">竜力の継承</text>
  </message>
  <message>
    <text xml:space="preserve">記録官</text>
  </message>
  <message>
    <text xml:space="preserve">ジョブマスター：ファイター</text>
  </message>
  <message>
    <text xml:space="preserve">よろず屋</text>
  </message>
  <message>
    <text xml:space="preserve">よろず屋</text>
  </message>
  <message>
    <text xml:space="preserve">冒険仲介係</text>
  </message>
  <message>
    <text xml:space="preserve">武器屋</text>
  </message>
  <message>
    <text xml:space="preserve">防具屋</text>
  </message>
  <message>
    <text xml:space="preserve">美容院</text>
  </message>
  <message>
    <text xml:space="preserve">素材屋</text>
  </message>
  <message>
    <text xml:space="preserve">道具屋</text>
  </message>
  <message>
    <text xml:space="preserve">バザー</text>
  </message>
  <message>
    <text xml:space="preserve">バザー</text>
  </message>
  <message>
    <text xml:space="preserve">バザー</text>
  </message>
  <message>
    <text xml:space="preserve">道具屋</text>
  </message>
  <message>
    <text xml:space="preserve">クラン酒場</text>
  </message>
  <message>
    <text xml:space="preserve">店員</text>
  </message>
  <message>
    <text xml:space="preserve">レスタニアニュース</text>
  </message>
  <message>
    <text xml:space="preserve">宿屋</text>
  </message>
  <message>
    <text xml:space="preserve">クラフト係官</text>
  </message>
  <message>
    <text xml:space="preserve">グランドミッション：グリッテン砦攻防戦</text>
  </message>
  <message>
    <text xml:space="preserve">転職・戦技補佐</text>
  </message>
  <message>
    <text xml:space="preserve">訓練官</text>
  </message>
  <message>
    <text xml:space="preserve">トレジャーズロット</text>
  </message>
  <message>
    <text xml:space="preserve">素材屋</text>
  </message>
  <message>
    <text xml:space="preserve">バザー</text>
  </message>
  <message>
    <text xml:space="preserve">グランドミッション：魔物のるつぼ</text>
  </message>
  <message>
    <text xml:space="preserve">道具屋</text>
  </message>
  <message>
    <text xml:space="preserve">道具屋</text>
  </message>
  <message>
    <text xml:space="preserve">素材屋</text>
  </message>
  <message>
    <text xml:space="preserve">道具屋</text>
  </message>
  <message>
    <text xml:space="preserve">宿・戦技補佐</text>
  </message>
  <message>
    <text xml:space="preserve">店員</text>
  </message>
  <message>
    <text xml:space="preserve">エリアマスター</text>
  </message>
  <message>
    <text xml:space="preserve">冒険仲介係</text>
  </message>
  <message>
    <text xml:space="preserve">道具屋</text>
  </message>
  <message>
    <text xml:space="preserve">宿・戦技補佐</text>
  </message>
  <message>
    <text xml:space="preserve">武具屋</text>
  </message>
  <message>
    <text xml:space="preserve">店員</text>
  </message>
  <message>
    <text xml:space="preserve">冒険仲介係</text>
  </message>
  <message>
    <text xml:space="preserve">エリアマスター</text>
  </message>
  <message>
    <text xml:space="preserve">素材屋</text>
  </message>
  <message>
    <text xml:space="preserve">よろず屋</text>
  </message>
  <message>
    <text xml:space="preserve">宿・戦技補佐</text>
  </message>
  <message>
    <text xml:space="preserve">冒険仲介係</text>
  </message>
  <message>
    <text xml:space="preserve">エリアマスター</text>
  </message>
  <message>
    <text xml:space="preserve">宿・戦技補佐</text>
  </message>
  <message>
    <text xml:space="preserve">よろず屋</text>
  </message>
  <message>
    <text xml:space="preserve">冒険仲介係</text>
  </message>
  <message>
    <text xml:space="preserve">エリアマスター</text>
  </message>
  <message>
    <text xml:space="preserve">素材屋</text>
  </message>
  <message>
    <text xml:space="preserve">武具屋</text>
  </message>
  <message>
    <text xml:space="preserve">道具屋</text>
  </message>
  <message>
    <text xml:space="preserve">宿・戦技補佐</text>
  </message>
  <message>
    <text xml:space="preserve">エリアマスター</text>
  </message>
  <message>
    <text xml:space="preserve">よろず屋</text>
  </message>
  <message>
    <text xml:space="preserve">泉の係官</text>
  </message>
  <message>
    <text xml:space="preserve">泉の係官</text>
  </message>
  <message>
    <text xml:space="preserve">泉の係官</text>
  </message>
  <message>
    <text xml:space="preserve">冒険仲介係</text>
  </message>
  <message>
    <text xml:space="preserve">受付</text>
  </message>
  <message>
    <text xml:space="preserve">よろず屋</text>
  </message>
  <message>
    <text xml:space="preserve">よろず屋</text>
  </message>
  <message>
    <text xml:space="preserve">宿・戦技補佐</text>
  </message>
  <message>
    <text xml:space="preserve">エリアマスター</text>
  </message>
  <message>
    <text xml:space="preserve">オーブ交換：珍品／素材</text>
  </message>
  <message>
    <text xml:space="preserve">よろず屋</text>
  </message>
  <message>
    <text xml:space="preserve">宿・戦技補佐</text>
  </message>
  <message>
    <text xml:space="preserve">よろず屋</text>
  </message>
  <message>
    <text xml:space="preserve">オーブ交換：クレスト</text>
  </message>
  <message>
    <text xml:space="preserve">ジョブマスター：プリースト</text>
  </message>
  <message>
    <text xml:space="preserve">冒険仲介係</text>
  </message>
  <message>
    <text xml:space="preserve">ジョブマスター：シールドセージ</text>
  </message>
  <message>
    <text xml:space="preserve">ジョブマスター：ソーサラー</text>
  </message>
  <message>
    <text xml:space="preserve">道具屋・ジョブマスター：ハンター</text>
  </message>
  <message>
    <text xml:space="preserve">ジョブマスター</text>
  </message>
  <message>
    <text xml:space="preserve">エリアマスター・宿</text>
  </message>
  <message>
    <text xml:space="preserve">復活力・ログインスタンプ</text>
  </message>
  <message>
    <text xml:space="preserve">よろず屋</text>
  </message>
  <message>
    <text xml:space="preserve">よろず屋</text>
  </message>
  <message>
    <text xml:space="preserve">現れしポーン</text>
  </message>
</resource>