<resource endian="Little" locale="0" unknown="0" tag="TextWeb">
  <message>
    <key>TUTORIAL_STEP_425</key>
    <original xml:space="preserve">　&lt;COL 78f5ff&gt;レスタニア第三節：「白竜よ永遠なれ」到達！&lt;/COL&gt;

　“３００年前より蘇りし災禍の主は
　　一人の覚者により討たれ、大いなる白竜は
　　石化の呪縛より放たれた――

　　しかし、それはただひとときの平穏
　　もう一つの災禍・黄金の竜は異空に舞い
　　レスタニアは未だ《理》の外にあり――”</original>
  </message>
  <message>
    <key>TUTORIAL_STEP_426</key>
    <original xml:space="preserve">覚者であるあなたの活躍により
古の錬金術師・ディアマンテスの野望は
潰えました

しかし、白竜と戦い力を奪った
真の災厄・黄金竜は未だ力を蓄え
レスタニアのどこかに存在しています

来たるべき黄金竜との決戦に向け
力を蓄え、装備を鍛えましょう</original>
  </message>
</resource>