<resource>
  <message>
    <key>q00020080_00_43</key>
    <original>あらたな異変</original>
    <translation>A Fresh Incident</translation>
  </message>
  <message>
    <key>q00020080_00_43</key>
    <original>魔赤島に渡り新たな魔物に襲われた
ガルドリンを救助する</original>
    <translation>Go to the aid of Gurdolin, who has been attacked
by strange new demons at Bloodbane Isle</translation>
  </message>
  <message>
    <key>q00020080_00_1735</key>
    <original>クラウスと話をする</original>
    <translation>Speak to Klaus</translation>
  </message>
  <message>
    <key>q00020080_00_1734</key>
    <original>魔赤島に向かいガルドリンを探し出す</original>
    <translation>Go to Bloodbane Isle and find Gurdolin</translation>
  </message>
  <message>
    <key>q00020080_00_1733</key>
    <original>出現した敵を討伐する</original>
    <translation>Defeat the enemy encountered</translation>
  </message>
  <message>
    <key>q00020080_00_1732</key>
    <original>謁見の間のジョゼフに報告する</original>
    <translation>Report to Joseph in Audience Chamber</translation>
  </message>
</resource>
