<resource endian="Little" locale="0" unknown="0" tag="TextWeb">
  <message>
    <key>q20010003_00_230</key>
    <text xml:space="preserve">The Sea-Watcher's Hand</text>
  </message>
  <message>
    <key>q20010003_00_230</key>
    <text xml:space="preserve">依頼者の願いを聞き入れ
物品を指定の場所に届ける</text>
  </message>
  <message>
    <key>q20010003_00_230</key>
    <text xml:space="preserve">From &lt;NAME AREA&gt;,
There are reports of someone who is begging for help.</text>
  </message>
  <message>
    <key>q20010003_00_230</key>
    <text xml:space="preserve">波の音を聞くと心が休まります
こういう場所はひとりで独占したいものです
頼みごとを抱えた人？
いやいや、そんな人と関わるのはごめんですよ
だ私は昨日、あのあたりに近づかなかったんです</text>
  </message>
  <message>
    <key>q20010003_00_897</key>
    <text xml:space="preserve">Visit the lighthouse keeper.</text>
  </message>
  <message>
    <key>q20010003_00_804</key>
    <text xml:space="preserve">Report back to the requester.</text>
  </message>
</resource>