<resource endian="Little" locale="0" unknown="0" tag="TextWeb">
  <message>
    <key>q60030002_00_58</key>
    <original xml:space="preserve">ミスリウ森林　試練：討伐！　魔獅子シンガ</original>
    <translation xml:space="preserve">Mysree Forest Trial: Elimination - Singa, The Ensorcelled One</translation>
  </message>
  <message>
    <key>q60030002_00_58</key>
    <original xml:space="preserve">ミスリウ森林の問題解決のため
ミスリウ鍾乳洞へ向かい脅威を排除する</original>
  </message>
  <message>
    <key>q60030002_00_1397</key>
    <original xml:space="preserve">ミスリウ鍾乳洞へ向かい脅威を発見する</original>
  </message>
  <message>
    <key>q60030002_00_1398</key>
    <original xml:space="preserve">脅威となる敵を掃討する</original>
    <translation xml:space="preserve">Defeat the enemy threat.</translation>
  </message>
  <message>
    <key>q60030002_00_1399</key>
    <original xml:space="preserve">リンウッド村のパトリシアに報告する</original>
  </message>
</resource>