<resource>
  <message>
    <key>q60203001_00_121</key>
    <original>ミスリウ森林　試練：黒き呪縛の殺意</original>
    <translation>Mysree Forest Trial: The Malice of the Accursed</translation>
  </message>
  <message>
    <key>q60203001_00_121</key>
    <original>ミスリウ森林の問題解決のため
ミスリウ古墳墓を調査し
魔物の正体を突き止める</original>
  </message>
  <message>
    <key>q60203001_00_1810</key>
    <original>ミスリウ古墳墓へ向かい魔物の正体を探る</original>
  </message>
  <message>
    <key>q60203001_00_1811</key>
    <original>発見した魔物を討伐する</original>
    <translation>Defeat the enemy encountered</translation>
  </message>
  <message>
    <key>q60203001_00_1809</key>
    <original>リンウッド村のパトリシアに報告する</original>
    <translation>Report back to Patricia in Lynwood village</translation>
  </message>
</resource>